coyaml/__init__.py
coyaml/__init__.pyi
coyaml/py.typed
coyaml/_internal/_config.py
coyaml/_internal/config.py
coyaml/_internal/inject.py
coyaml/_internal/node.py
coyaml/_internal/registry.py
coyaml/_internal/search.py
coyaml/sources/base.py
coyaml/sources/env.py
coyaml/sources/yaml.py
coyaml/utils/merge.py
coyaml-0.11.0.dist-info/METADATA
coyaml-0.11.0.dist-info/WHEEL
coyaml-0.11.0.dist-info/licenses/LICENSE
coyaml-0.11.0.dist-info/RECORD
