Metadata-Version: 2.4
Name: coyaml
Version: 0.11.0
Summary: Yaml configuration library for python
Project-URL: Repository, https://github.com/kuruhuru/coyaml
Project-URL: Documentation, https://coyaml.readthedocs.io/en/latest/
Project-URL: Homepage, https://coyaml.readthedocs.io/
Author-email: Petr Matyukov <kuruhuru@gmail.com>
License: Apache-2.0
License-File: LICENSE
Requires-Python: <3.12,>=3.10.6
Requires-Dist: pydantic<3,>=2
Requires-Dist: python-dotenv>=1.1.0
Requires-Dist: types-pyyaml>=6.0.12.20240311
